<annotation>
	<folder>Food</folder>
	<filename>Food206.jpg</filename>
	<path>/home/reshyurem/Documents/Food/Food206.jpg</path>
	<source>
		<database>Unknown</database>
	</source>
	<size>
		<width>5256</width>
		<height>3504</height>
		<depth>3</depth>
	</size>
	<segmented>0</segmented>
	<object>
		<name>dosa</name>
		<pose>Unspecified</pose>
		<truncated>0</truncated>
		<difficult>0</difficult>
		<bndbox>
			<xmin>944</xmin>
			<ymin>724</ymin>
			<xmax>2043</xmax>
			<ymax>3244</ymax>
		</bndbox>
	</object>
	<object>
		<name>dosa</name>
		<pose>Unspecified</pose>
		<truncated>0</truncated>
		<difficult>0</difficult>
		<bndbox>
			<xmin>1916</xmin>
			<ymin>478</ymin>
			<xmax>2789</xmax>
			<ymax>3123</ymax>
		</bndbox>
	</object>
	<object>
		<name>dosa</name>
		<pose>Unspecified</pose>
		<truncated>0</truncated>
		<difficult>0</difficult>
		<bndbox>
			<xmin>2553</xmin>
			<ymin>392</ymin>
			<xmax>3423</xmax>
			<ymax>3299</ymax>
		</bndbox>
	</object>
</annotation>
