<annotation>
	<folder>Food</folder>
	<filename>Food307.jpg</filename>
	<path>/home/reshyurem/Documents/Food/Food307.jpg</path>
	<source>
		<database>Unknown</database>
	</source>
	<size>
		<width>682</width>
		<height>1024</height>
		<depth>3</depth>
	</size>
	<segmented>0</segmented>
	<object>
		<name>dosa</name>
		<pose>Unspecified</pose>
		<truncated>0</truncated>
		<difficult>0</difficult>
		<bndbox>
			<xmin>257</xmin>
			<ymin>163</ymin>
			<xmax>668</xmax>
			<ymax>870</ymax>
		</bndbox>
	</object>
	<object>
		<name>chutney</name>
		<pose>Unspecified</pose>
		<truncated>0</truncated>
		<difficult>0</difficult>
		<bndbox>
			<xmin>117</xmin>
			<ymin>551</ymin>
			<xmax>320</xmax>
			<ymax>746</ymax>
		</bndbox>
	</object>
</annotation>
